Metadata-Version: 2.1
Name: configura
Version: 0.1
Summary: Configura is a Python configuration library that enables you to convert a folder of .json files into an easily accessible configuration folder.
Home-page: https://github.com/bossauh/configura
Download-URL: https://github.com/bossauh/configura/archive/refs/tags/v_01.tar.gz
Author: Philippe Mathew
Author-email: philmattdev@gmail.com
License: MIT
Keywords: config
License-File: LICENSE
